CHANGES.rst
CONTRIBUTORS.rst
LICENSE.rst
MANIFEST.in
README.rst
TODO.rst
setup.cfg
setup.py
collective/__init__.py
collective.recipe.cmd.egg-info/PKG-INFO
collective.recipe.cmd.egg-info/SOURCES.txt
collective.recipe.cmd.egg-info/dependency_links.txt
collective.recipe.cmd.egg-info/entry_points.txt
collective.recipe.cmd.egg-info/namespace_packages.txt
collective.recipe.cmd.egg-info/not-zip-safe
collective.recipe.cmd.egg-info/requires.txt
collective.recipe.cmd.egg-info/top_level.txt
collective/recipe/__init__.py
collective/recipe/cmd/__init__.py
collective/recipe/cmd/test.txt
collective/recipe/cmd/tests/__init__.py
collective/recipe/cmd/tests/test_docs.py