Metadata-Version: 1.1
Name: collective.recipe.cmd
Version: 0.8
Summary: A Buildout recipe to execute commands in the console user interface
Home-page: http://plone.org/products/collective-recipes
Author: Gael Pasgrimaud
Author-email: gael@gawel.org
License: BSD
Keywords: buildout recipe
Platform: UNKNOWN
Classifier: Framework :: Buildout
Classifier: Intended Audience :: Developers
Classifier: Topic :: Software Development :: Build Tools
Classifier: Topic :: Software Development :: Libraries :: Python Modules
Classifier: License :: OSI Approved :: BSD License
